<?xml version="1.0" encoding="iso-8859-1"?>
<!DOCTYPE library SYSTEM "library.dtd">
<!-- autogenerated by fdtrans v50.9 -->
<library name="usbhcd" basename="USBHCDBase" openname="usbhcd.library">
	<include>exec/types.h</include>
	<interface name="main" version="1.0" struct="USBHCDIFace" prefix="_USBHCD_" asmprefix="IUSBHCD" global="IUSBHCD">
		<method name="Obtain" result="ULONG"/>
		<method name="Release" result="ULONG"/>
		<method name="Expunge" result="void" status="unimplemented"/>
		<method name="Clone" result="struct Interface *" status="unimplemented"/>
		<method name="USBHCAddFunctionA" result="APTR">
			<arg name="hcunit" type="APTR"/>
			<arg name="hchub" type="APTR"/>
			<arg name="usfkt" type="APTR"/>
			<arg name="taglist" type="struct TagItem *"/>
		</method>
		<method name="USBHCAddFunction" result="APTR">
			<arg name="hcunit" type="APTR"/>
			<arg name="hchub" type="APTR"/>
			<arg name="usfkt" type="APTR"/>
			<vararg name="taglist" type="ULONG"/>
		</method>
		<method name="USBHCRemFunction" result="void">
			<arg name="hcunit" type="APTR"/>
			<arg name="hcfkt" type="APTR"/>
		</method>
		<method name="USBHCAddEndPointA" result="APTR">
			<arg name="hcunit" type="APTR"/>
			<arg name="hcfkt" type="APTR"/>
			<arg name="usep" type="APTR"/>
			<arg name="epnum" type="LONG"/>
			<arg name="taglist" type="struct TagItem *"/>
		</method>
		<method name="USBHCAddEndPoint" result="APTR">
			<arg name="hcunit" type="APTR"/>
			<arg name="hcfkt" type="APTR"/>
			<arg name="usep" type="APTR"/>
			<arg name="epnum" type="LONG"/>
			<vararg name="taglist" type="ULONG"/>
		</method>
		<method name="USBHCRemEndPoint" result="void">
			<arg name="hcunit" type="APTR"/>
			<arg name="hcep" type="APTR"/>
		</method>
		<method name="USBHCGetAttrsA" result="void">
			<arg name="taglist" type="struct TagItem *"/>
		</method>
		<method name="USBHCGetAttrs" result="void">
			<vararg name="taglist" type="ULONG"/>
		</method>
		<method name="USBHCInitRootHubA" result="LONG">
			<arg name="hcunit" type="APTR"/>
			<arg name="usifc" type="struct UsbRawInterface *"/>
			<arg name="hcfkt" type="APTR *"/>
			<arg name="taglist" type="struct TagItem *"/>
		</method>
		<method name="USBHCInitRootHub" result="LONG">
			<arg name="hcunit" type="APTR"/>
			<arg name="usifc" type="struct UsbRawInterface *"/>
			<arg name="hcfkt" type="APTR *"/>
			<vararg name="taglist" type="ULONG"/>
		</method>
		<method name="USBHCUninitRootHub" result="void">
			<arg name="hcunit" type="APTR"/>
			<arg name="hcfkt" type="APTR"/>
		</method>
	</interface>
</library>
